LICENSE
mcanitexgen/__init__.py
mcanitexgen/__main__.py
mcanitexgen/animation/__init__.py
mcanitexgen/animation/generator.py
mcanitexgen/animation/parser.py
mcanitexgen/animation/utils.py
mcanitexgen/cli.py
mcanitexgen/gif/__init__.py
mcanitexgen/gif/generator.py
mcanitexgen/gif/images2gif.py
mcanitexgen/integration/__init__.py
mcanitexgen/integration/beet.py
mcanitexgen-1.2.3.dist-info/entry_points.txt
mcanitexgen-1.2.3.dist-info/LICENSE
mcanitexgen-1.2.3.dist-info/WHEEL
mcanitexgen-1.2.3.dist-info/METADATA
mcanitexgen-1.2.3.dist-info/RECORD
