Metadata-Version: 2.1
Name: mcanitexgen
Version: 1.2.3
Summary: An animation generator for Minecraft .mcmeta files
Home-page: https://github.com/OrangeUtan/mcanitexgen
License: MIT
Keywords: minecraft,animation,mcmeta
Author: Oran9eUtan
Author-email: oran9eutan@gmail.com
Requires-Python: >=3.8,<4.0
Classifier: License :: OSI Approved :: MIT License
Classifier: Programming Language :: Python :: 3
Classifier: Programming Language :: Python :: 3.8
Classifier: Programming Language :: Python :: 3.9
Requires-Dist: Pillow (>=8.1.2,<9.0.0)
Requires-Dist: numpy (>=1.20.1,<2.0.0)
Requires-Dist: typer (>=0.3.2,<0.4.0)
Project-URL: Repository, https://github.com/OrangeUtan/mcanitexgen
